[
  {
    "title": "Amistoso: \nRD del Congo vs Dinamarca - Disney+",
    "url": "https://agvyby.fubohd.com:443/espn/mono.m3u8?token=0836e9319edd6948a3a61671164f29355ea9705a-73-1780502020-1780484020",
    "type": "event",
    "source": "https://tvtvhd.com/canales.php?stream=espn",
    "country": "Amistoso",
    "event_description": "Amistoso: \nRD del Congo vs Dinamarca",
    "event_hour": "15:00",
    "event_date": "2026-06-03",
    "embed_name": "Disney+"
  },
  {
    "title": "Amistoso: \nPaíses Bajos vs Argelia - ESPN",
    "url": "https://qzv4jmsc.fubohd.com:443/espn/mono.m3u8?token=3122bd067f33ed1afdb132d166f4a2644bc613f1-4f-1780502021-1780484021",
    "type": "event",
    "source": "https://tvtvhd.com/canales.php?stream=espn",
    "country": "Amistoso",
    "event_description": "Amistoso: \nPaíses Bajos vs Argelia",
    "event_hour": "15:45",
    "event_date": "2026-06-03",
    "embed_name": "ESPN"
  },
  {
    "title": "Amistoso: \nPaíses Bajos vs Argelia - ESPN AR┃OP2",
    "url": "https://cgxheq.fubohd.com:443/espn/mono.m3u8?token=ebe43f8b4d35c8a5bd84c481c6b438ffdb9f92f8-bd-1780502021-1780484021",
    "type": "event",
    "source": "https://tvtvhd.com/vivo/canal.php?stream=espn",
    "country": "Amistoso",
    "event_description": "Amistoso: \nPaíses Bajos vs Argelia",
    "event_hour": "15:45",
    "event_date": "2026-06-03",
    "embed_name": "ESPN AR┃OP2"
  },
  {
    "title": "Amistoso: \nPaíses Bajos vs Argelia - ESPN AR┃OP3",
    "url": "https://qzv4jmsc.fubohd.com:443/espn/mono.m3u8?token=70cde494e052eaecb99abfa76f3cb68c56e0cc2c-c5-1780502021-1780484021",
    "type": "event",
    "source": "https://tvtvhd.com/vivo/canales.php?stream=espn",
    "country": "Amistoso",
    "event_description": "Amistoso: \nPaíses Bajos vs Argelia",
    "event_hour": "15:45",
    "event_date": "2026-06-03",
    "embed_name": "ESPN AR┃OP3"
  },
  {
    "title": "Amistoso: \nPolonia vs Nigeria - Sportv BR",
    "url": "https://aw1wcm92zq.fubohd.com:443/sportv/mono.m3u8?token=5663c421279118c18fbdaef217ea8bb003a06bcc-fa-1780502022-1780484022",
    "type": "event",
    "source": "https://tvtvhd.com/vivo/canales.php?stream=sportv",
    "country": "Amistoso",
    "event_description": "Amistoso: \nPolonia vs Nigeria",
    "event_hour": "15:45",
    "event_date": "2026-06-03",
    "embed_name": "Sportv BR"
  },
  {
    "title": "Torneo de Reserva: \nRosario Central  vs Racing Club - ESPN 3",
    "url": "https://a2vlca.fubohd.com:443/espn3/mono.m3u8?token=993c309ab7574a1f67e35593c39df9c5666cd062-ee-1780502022-1780484022",
    "type": "event",
    "source": "https://tvtvhd.com/canales.php?stream=espn3",
    "country": "Argentina",
    "event_description": "Torneo de Reserva: \nRosario Central  vs Racing Club",
    "event_hour": "15:00",
    "event_date": "2026-06-03",
    "embed_name": "ESPN 3"
  },
  {
    "title": "Torneo de Reserva: \nRosario Central  vs Racing Club - ESPN 3 | OP2",
    "url": "https://anvtcax.fubohd.com:443/espn3/mono.m3u8?token=5a5b85a9b757e9a1329e2631b7fac90bb3eb22f5-91-1780502023-1780484023",
    "type": "event",
    "source": "https://tvtvhd.com/vivo/canal.php?stream=espn3",
    "country": "Argentina",
    "event_description": "Torneo de Reserva: \nRosario Central  vs Racing Club",
    "event_hour": "15:00",
    "event_date": "2026-06-03",
    "embed_name": "ESPN 3 | OP2"
  },
  {
    "title": "Torneo de Reserva: \nRosario Central  vs Racing Club - ESPN 3 | OP3",
    "url": "https://agvyby.fubohd.com:443/espn3/mono.m3u8?token=dbf69b3dda26aed9c92895261a78a42b427f11e4-7e-1780502023-1780484023",
    "type": "event",
    "source": "https://tvtvhd.com/vivo/canales.php?stream=espn3",
    "country": "Argentina",
    "event_description": "Torneo de Reserva: \nRosario Central  vs Racing Club",
    "event_hour": "15:00",
    "event_date": "2026-06-03",
    "embed_name": "ESPN 3 | OP3"
  },
  {
    "title": "Torneo Maurice Revello Sub-20 : \nJapón  vs Portugal - FOX Deportes",
    "url": "https://ym9yzq.fubohd.com:443/foxdeportes/mono.m3u8?token=cfd37942035ac03ac27811c573237a02d9c50e67-df-1780502024-1780484024",
    "type": "event",
    "source": "https://tvtvhd.com/vivo/canal.php?stream=foxdeportes",
    "country": "Eliminatorias AFC",
    "event_description": "Torneo Maurice Revello Sub-20 : \nJapón  vs Portugal",
    "event_hour": "10:00",
    "event_date": "2026-06-03",
    "embed_name": "FOX Deportes"
  },
  {
    "title": "Torneo Maurice Revello Sub-20 : \nJapón  vs Portugal - FOX Deportes | OP2",
    "url": "https://cgxheq.fubohd.com:443/foxdeportes/mono.m3u8?token=1cb3ee4f5903d2894f3c37df75616e319dec53a1-a5-1780502024-1780484024",
    "type": "event",
    "source": "https://tvtvhd.com/vivo/canal.php?stream=foxdeportes",
    "country": "Eliminatorias AFC",
    "event_description": "Torneo Maurice Revello Sub-20 : \nJapón  vs Portugal",
    "event_hour": "10:00",
    "event_date": "2026-06-03",
    "embed_name": "FOX Deportes | OP2"
  },
  {
    "title": "Torneo Maurice Revello Sub-20 : \nJapón  vs Portugal - FOX Deportes | OP3",
    "url": "https://tyg2mnl9.fubohd.com:443/foxdeportes/mono.m3u8?token=d5610c07f4190fd608cbed107a2def4cb259da0a-69-1780502024-1780484024",
    "type": "event",
    "source": "https://tvtvhd.com/vivo/canales.php?stream=foxdeportes",
    "country": "Eliminatorias AFC",
    "event_description": "Torneo Maurice Revello Sub-20 : \nJapón  vs Portugal",
    "event_hour": "10:00",
    "event_date": "2026-06-03",
    "embed_name": "FOX Deportes | OP3"
  },
  {
    "title": "Tenis – Roland Garros – Día #11 – Cuartos de Final - ESPN 2 MX",
    "url": "https://qzv4jmsc.fubohd.com:443/espn2mx/mono.m3u8?token=5c960c0f941a34f10d6612ed04a91b1f905099e4-80-1780502025-1780484025",
    "type": "event",
    "source": "https://tvtvhd.com/canales.php?stream=espn2mx",
    "country": "Tennis",
    "event_description": "Tenis – Roland Garros – Día #11 – Cuartos de Final",
    "event_hour": "06:00",
    "event_date": "2026-06-03",
    "embed_name": "ESPN 2 MX"
  },
  {
    "title": "Tenis – Roland Garros – Día #11 – Cuartos de Final - ESPN 2",
    "url": "https://ag9wzq.fubohd.com:443/espn2/mono.m3u8?token=47776f1fa26b281d9b7fbbf32ca4de3acd2d18fa-6a-1780502025-1780484025",
    "type": "event",
    "source": "https://tvtvhd.com/canales.php?stream=espn2",
    "country": "Tennis",
    "event_description": "Tenis – Roland Garros – Día #11 – Cuartos de Final",
    "event_hour": "06:00",
    "event_date": "2026-06-03",
    "embed_name": "ESPN 2"
  },
  {
    "title": "Tenis – Roland Garros – Día #11 – Cuartos de Final - ESPN 2 | OP2",
    "url": "https://c2nvdxq.fubohd.com:443/espn2/mono.m3u8?token=7279b77c8d523ca70651fd1bcdd8754029b594ee-c8-1780502026-1780484026",
    "type": "event",
    "source": "https://tvtvhd.com/vivo/canal.php?stream=espn2",
    "country": "Tennis",
    "event_description": "Tenis – Roland Garros – Día #11 – Cuartos de Final",
    "event_hour": "06:00",
    "event_date": "2026-06-03",
    "embed_name": "ESPN 2 | OP2"
  },
  {
    "title": "Tenis – Roland Garros – Día #11 – Cuartos de Final - ESPN 2 | OP3",
    "url": "https://c2nvdxq.fubohd.com:443/espn2/mono.m3u8?token=019b8c63b5543173f30e0704d335eb967961082e-b9-1780502026-1780484026",
    "type": "event",
    "source": "https://tvtvhd.com/vivo/canales.php?stream=espn2",
    "country": "Tennis",
    "event_description": "Tenis – Roland Garros – Día #11 – Cuartos de Final",
    "event_hour": "06:00",
    "event_date": "2026-06-03",
    "embed_name": "ESPN 2 | OP3"
  },
  {
    "title": "Tenis – Roland Garros – Día #11 – Cuartos de Final - ESPN 2",
    "url": "https://wp9xqedt.fubohd.com:443/espn2/mono.m3u8?token=23e4fa066f8728ef7e3ca1cbf83f0f205fd33708-9a-1780502027-1780484027",
    "type": "event",
    "source": "https://tvtvhd.com/canales.php?stream=espn2",
    "country": "Tennis",
    "event_description": "Tenis – Roland Garros – Día #11 – Cuartos de Final",
    "event_hour": "15:00",
    "event_date": "2026-06-03",
    "embed_name": "ESPN 2"
  },
  {
    "title": "Tenis – Roland Garros – Día #11 – Cuartos de Final - ESPN 2 | OP2",
    "url": "https://a2vlca.fubohd.com:443/espn2/mono.m3u8?token=8764700274a9c1c7fe5712c2508f9ff17fb62ade-ed-1780502027-1780484027",
    "type": "event",
    "source": "https://tvtvhd.com/vivo/canal.php?stream=espn2",
    "country": "Tennis",
    "event_description": "Tenis – Roland Garros – Día #11 – Cuartos de Final",
    "event_hour": "15:00",
    "event_date": "2026-06-03",
    "embed_name": "ESPN 2 | OP2"
  },
  {
    "title": "Tenis – Roland Garros – Día #11 – Cuartos de Final - ESPN 2 | OP3",
    "url": "https://x4bnd7lq.fubohd.com:443/espn2/mono.m3u8?token=d9990acfee2cb086e11ddced9c7fb05e7400c239-e4-1780502027-1780484027",
    "type": "event",
    "source": "https://tvtvhd.com/vivo/canales.php?stream=espn2",
    "country": "Tennis",
    "event_description": "Tenis – Roland Garros – Día #11 – Cuartos de Final",
    "event_hour": "15:00",
    "event_date": "2026-06-03",
    "embed_name": "ESPN 2 | OP3"
  },
  {
    "title": "Amistoso: \nAlbania vs Israel - Disney+",
    "url": "https://agvyby.fubohd.com:443/espn/mono.m3u8?token=1e896796feb110b191042835c6eb88f6b7564ed9-74-1780502028-1780484028",
    "type": "event",
    "source": "https://tvtvhd.com/canales.php?stream=espn",
    "country": "Amistoso",
    "event_description": "Amistoso: \nAlbania vs Israel",
    "event_hour": "15:00",
    "event_date": "2026-06-03",
    "embed_name": "Disney+"
  },
  {
    "title": "Amistoso: \nLuxemburgo vs Italia - Disney+",
    "url": "https://a2vlca.fubohd.com:443/espn/mono.m3u8?token=0c1ae2ea587b3636431a76fa69d6f72db1328945-9f-1780502028-1780484028",
    "type": "event",
    "source": "https://tvtvhd.com/canales.php?stream=espn",
    "country": "Amistoso",
    "event_description": "Amistoso: \nLuxemburgo vs Italia",
    "event_hour": "15:45",
    "event_date": "2026-06-03",
    "embed_name": "Disney+"
  },
  {
    "title": "Primera División: \nGualberto Villarroel SJ vs Real Tomayapo - Futbol Canal",
    "url": "https://cxm2.futbolonlinehd.com:443/even1/mono.m3u8?token=496459a493092e1a6847565516126bb5a7eeebda-dc-1780502029-1780484029",
    "type": "event",
    "source": "https://tvtvhd.com/tv/canal.php?stream=even1",
    "country": "Bolivia",
    "event_description": "Primera División: \nGualberto Villarroel SJ vs Real Tomayapo",
    "event_hour": "19:00",
    "event_date": "2026-06-03",
    "embed_name": "Futbol Canal"
  },
  {
    "title": "Primera División: \nGualberto Villarroel SJ vs Real Tomayapo - Futbol Canal | OP2",
    "url": "https://cxm5.futbolonlinehd.com:443/even1/mono.m3u8?token=dafd064eee4b3d9a45ae9f43f3762da72285f524-3b-1780502029-1780484029",
    "type": "event",
    "source": "https://tvtvhd.com/tv/canal.php?stream=even1",
    "country": "Bolivia",
    "event_description": "Primera División: \nGualberto Villarroel SJ vs Real Tomayapo",
    "event_hour": "19:00",
    "event_date": "2026-06-03",
    "embed_name": "Futbol Canal | OP2"
  },
  {
    "title": "Primera División: \nGualberto Villarroel SJ vs Real Tomayapo - Futbol Canal | OP3",
    "url": "https://cxm4.futbolonlinehd.com:443/even1/mono.m3u8?token=f018b9befe8437fa3330792e184cdbfbbf9a60fb-5a-1780502030-1780484030",
    "type": "event",
    "source": "https://tvtvhd.com/tv/canal.php?stream=even1",
    "country": "Bolivia",
    "event_description": "Primera División: \nGualberto Villarroel SJ vs Real Tomayapo",
    "event_hour": "19:00",
    "event_date": "2026-06-03",
    "embed_name": "Futbol Canal | OP3"
  },
  {
    "title": "Primera División: \nReal Potosí vs ABB - Futbol Canal",
    "url": "https://cxm1.futbolonlinehd.com:443/even1/mono.m3u8?token=14259e9d99f38d6268025e50b194d846bc4463e8-bb-1780502030-1780484030",
    "type": "event",
    "source": "https://tvtvhd.com/tv/canal.php?stream=even1",
    "country": "Bolivia",
    "event_description": "Primera División: \nReal Potosí vs ABB",
    "event_hour": "21:00",
    "event_date": "2026-06-03",
    "embed_name": "Futbol Canal"
  },
  {
    "title": "Primera División: \nReal Potosí vs ABB - Futbol Canal | OP2",
    "url": "https://cxm2.futbolonlinehd.com:443/even1/mono.m3u8?token=661cbd8f84849ba8129eff5e9345c52201ec4c2b-1f-1780502030-1780484030",
    "type": "event",
    "source": "https://tvtvhd.com/tv/canal.php?stream=even1",
    "country": "Bolivia",
    "event_description": "Primera División: \nReal Potosí vs ABB",
    "event_hour": "21:00",
    "event_date": "2026-06-03",
    "embed_name": "Futbol Canal | OP2"
  },
  {
    "title": "Primera División: \nReal Potosí vs ABB - Futbol Canal | OP3",
    "url": "https://cxm4.futbolonlinehd.com:443/even1/mono.m3u8?token=e47059cb7ab9f679adc1288ed545fa44373bdb1b-37-1780502031-1780484031",
    "type": "event",
    "source": "https://tvtvhd.com/tv/canal.php?stream=even1",
    "country": "Bolivia",
    "event_description": "Primera División: \nReal Potosí vs ABB",
    "event_hour": "21:00",
    "event_date": "2026-06-03",
    "embed_name": "Futbol Canal | OP3"
  },
  {
    "title": "Copa Argentina: \nSan Lorenzo vs Deportivo Riestra - TYC Sports",
    "url": "https://aw1wcm92zq.fubohd.com:443/tycsports/mono.m3u8?token=9ec3e71f060052d03e021cb1fa9fdc3f716c5ecb-2f-1780502031-1780484031",
    "type": "event",
    "source": "https://tvtvhd.com/canales.php?stream=tycsports",
    "country": "Argentina",
    "event_description": "Copa Argentina: \nSan Lorenzo vs Deportivo Riestra",
    "event_hour": "21:10",
    "event_date": "2026-06-03",
    "embed_name": "TYC Sports"
  },
  {
    "title": "Copa Argentina: \nSan Lorenzo vs Deportivo Riestra - TyC Sports | OP2",
    "url": "https://ym9yzq.fubohd.com:443/tycsports/mono.m3u8?token=197717f60c6b87eae690a3b2562fff89a517b13f-ae-1780502032-1780484032",
    "type": "event",
    "source": "https://tvtvhd.com/canales.php?stream=tycsports",
    "country": "Argentina",
    "event_description": "Copa Argentina: \nSan Lorenzo vs Deportivo Riestra",
    "event_hour": "21:10",
    "event_date": "2026-06-03",
    "embed_name": "TyC Sports | OP2"
  },
  {
    "title": "Copa Argentina: \nSan Lorenzo vs Deportivo Riestra - TYC Sports | OP3",
    "url": "https://rm8zcvk3.fubohd.com:443/tycsports/mono.m3u8?token=9b8bf48a5d1e0f736b7ddbedabb86f0502245a2b-20-1780502032-1780484032",
    "type": "event",
    "source": "https://tvtvhd.com/canales.php?stream=tycsports",
    "country": "Argentina",
    "event_description": "Copa Argentina: \nSan Lorenzo vs Deportivo Riestra",
    "event_hour": "21:10",
    "event_date": "2026-06-03",
    "embed_name": "TYC Sports | OP3"
  },
  {
    "title": "Copa Argentina: \nSan Lorenzo vs Deportivo Riestra - TyC Sports Internacional",
    "url": "https://wp9xqedt.fubohd.com:443/tycinternacional/mono.m3u8?token=b507930545968edb7fe24f1ead78c9c9d7ab7b03-24-1780502032-1780484032",
    "type": "event",
    "source": "https://tvtvhd.com/canales.php?stream=tycinternacional",
    "country": "Argentina",
    "event_description": "Copa Argentina: \nSan Lorenzo vs Deportivo Riestra",
    "event_hour": "21:10",
    "event_date": "2026-06-03",
    "embed_name": "TyC Sports Internacional"
  },
  {
    "title": "Copa Argentina: \nSan Lorenzo vs Deportivo Riestra - TyC Sports Internacional | OP2",
    "url": "https://ag9wzq.fubohd.com:443/tycinternacional/mono.m3u8?token=1168ef3db670b5fc84c99f33b0c231b01db683a7-7b-1780502033-1780484033",
    "type": "event",
    "source": "https://tvtvhd.com/vivo/canal.php?stream=tycinternacional",
    "country": "Argentina",
    "event_description": "Copa Argentina: \nSan Lorenzo vs Deportivo Riestra",
    "event_hour": "21:10",
    "event_date": "2026-06-03",
    "embed_name": "TyC Sports Internacional | OP2"
  },
  {
    "title": "Copa Argentina: \nSan Lorenzo vs Deportivo Riestra - TyC Sports International | OP3",
    "url": "https://dw5pdgvk.fubohd.com:443/tycinternacional/mono.m3u8?token=7fa7512fd80826c1fd3e4e7a6dadf32e18a8df5a-2a-1780502033-1780484033",
    "type": "event",
    "source": "https://tvtvhd.com/vivo/canales.php?stream=tycinternacional",
    "country": "Argentina",
    "event_description": "Copa Argentina: \nSan Lorenzo vs Deportivo Riestra",
    "event_hour": "21:10",
    "event_date": "2026-06-03",
    "embed_name": "TyC Sports International | OP3"
  },
  {
    "title": "Copa Ecuador: \nGualaceo vs Mushuc Runa - Zapping TV",
    "url": "https://cxm3.futbolonlinehd.com:443/even3/mono.m3u8?token=c6def2e3a79cfc8cb6f70df60c46948816674c6a-1f-1780502034-1780484034",
    "type": "event",
    "source": "https://tvtvhd.com/tv/canal.php?stream=even3",
    "country": "Ecuador",
    "event_description": "Copa Ecuador: \nGualaceo vs Mushuc Runa",
    "event_hour": "17:30",
    "event_date": "2026-06-03",
    "embed_name": "Zapping TV"
  },
  {
    "title": "Copa Ecuador: \nGualaceo vs Mushuc Runa - ECDF LigaPro",
    "url": "https://rm8zcvk3.fubohd.com:443/ecdf_ligapro/mono.m3u8?token=960ae3510f258114caac991ed5d077ef15f13860-52-1780502034-1780484034",
    "type": "event",
    "source": "https://tvtvhd.com/canales.php?stream=ecdf_ligapro",
    "country": "Ecuador",
    "event_description": "Copa Ecuador: \nGualaceo vs Mushuc Runa",
    "event_hour": "17:30",
    "event_date": "2026-06-03",
    "embed_name": "ECDF LigaPro"
  },
  {
    "title": "Torneo de Reserva: \nBoca Juniors  vs Defensa y Justicia - TNT Sports",
    "url": "https://ag9wzq.fubohd.com:443/tntsports/mono.m3u8?token=6078589fc90542d3e0b08c11b2a9fc29b0e91116-14-1780502035-1780484035",
    "type": "event",
    "source": "https://tvtvhd.com/canales.php?stream=tntsports",
    "country": "Argentina",
    "event_description": "Torneo de Reserva: \nBoca Juniors  vs Defensa y Justicia",
    "event_hour": "19:00",
    "event_date": "2026-06-03",
    "embed_name": "TNT Sports"
  },
  {
    "title": "Torneo de Reserva: \nBoca Juniors  vs Defensa y Justicia - TNT Sports | OP2",
    "url": "https://dw5pdgvk.fubohd.com:443/tntsports/mono.m3u8?token=e74ade375003d7ebb24368b29d68563d8ac61321-ad-1780502035-1780484035",
    "type": "event",
    "source": "https://tvtvhd.com/canales.php?stream=tntsports",
    "country": "Argentina",
    "event_description": "Torneo de Reserva: \nBoca Juniors  vs Defensa y Justicia",
    "event_hour": "19:00",
    "event_date": "2026-06-03",
    "embed_name": "TNT Sports | OP2"
  },
  {
    "title": "Torneo de Reserva: \nBoca Juniors  vs Defensa y Justicia - TNT Sports | OP3",
    "url": "https://x4bnd7lq.fubohd.com:443/tntsports/mono.m3u8?token=d6cd4acb592620b606f79a1ceee7eabc01dc82fc-75-1780502035-1780484035",
    "type": "event",
    "source": "https://tvtvhd.com/canales.php?stream=tntsports",
    "country": "Argentina",
    "event_description": "Torneo de Reserva: \nBoca Juniors  vs Defensa y Justicia",
    "event_hour": "19:00",
    "event_date": "2026-06-03",
    "embed_name": "TNT Sports | OP3"
  },
  {
    "title": "Torneo Maurice Revello Sub-20 : \nCosta de Marfil  vs Venezuela - FOX Deportes",
    "url": "https://qzv4jmsc.fubohd.com:443/foxdeportes/mono.m3u8?token=326fd621cf30bb8824af1420226fe927b48fd742-f7-1780502036-1780484036",
    "type": "event",
    "source": "https://tvtvhd.com/vivo/canal.php?stream=foxdeportes",
    "country": "Eliminatorias AFC",
    "event_description": "Torneo Maurice Revello Sub-20 : \nCosta de Marfil  vs Venezuela",
    "event_hour": "13:30",
    "event_date": "2026-06-03",
    "embed_name": "FOX Deportes"
  },
  {
    "title": "Torneo Maurice Revello Sub-20 : \nCosta de Marfil  vs Venezuela - FOX Deportes | OP2",
    "url": "https://tyg2mnl9.fubohd.com:443/foxdeportes/mono.m3u8?token=9379a8b30e458a7820376d5c0663ff85c053c89f-be-1780502036-1780484036",
    "type": "event",
    "source": "https://tvtvhd.com/vivo/canal.php?stream=foxdeportes",
    "country": "Eliminatorias AFC",
    "event_description": "Torneo Maurice Revello Sub-20 : \nCosta de Marfil  vs Venezuela",
    "event_hour": "13:30",
    "event_date": "2026-06-03",
    "embed_name": "FOX Deportes | OP2"
  },
  {
    "title": "Torneo Maurice Revello Sub-20 : \nCosta de Marfil  vs Venezuela - FOX Deportes | OP3",
    "url": "https://tyg2mnl9.fubohd.com:443/foxdeportes/mono.m3u8?token=321a5326a99fd75df2931d910b14e23865205a32-2a-1780502037-1780484037",
    "type": "event",
    "source": "https://tvtvhd.com/vivo/canales.php?stream=foxdeportes",
    "country": "Eliminatorias AFC",
    "event_description": "Torneo Maurice Revello Sub-20 : \nCosta de Marfil  vs Venezuela",
    "event_hour": "13:30",
    "event_date": "2026-06-03",
    "embed_name": "FOX Deportes | OP3"
  },
  {
    "title": " MLB – Minnesota Twins vs Chicago White Sox - ESPN 5",
    "url": "https://aw1wcm92zq.fubohd.com:443/espn5/mono.m3u8?token=b221fd6b28ccbc0eb51bf4676b4b660425c65aca-ad-1780502037-1780484037",
    "type": "event",
    "source": "https://tvtvhd.com/canales.php?stream=espn5",
    "country": "MLB Preseason",
    "event_description": " MLB – Minnesota Twins vs Chicago White Sox",
    "event_hour": "14:30",
    "event_date": "2026-06-03",
    "embed_name": "ESPN 5"
  },
  {
    "title": " MLB – Minnesota Twins vs Chicago White Sox - ESPN 5 | OP2",
    "url": "https://bGFuZQ.fubohd.com:443/espn5/mono.m3u8?token=b15fb8fdf62d2c789621261ffca0a4840f38de07-ca-1780502038-1780484038",
    "type": "event",
    "source": "https://tvtvhd.com/vivo/canal.php?stream=espn5",
    "country": "MLB Preseason",
    "event_description": " MLB – Minnesota Twins vs Chicago White Sox",
    "event_hour": "14:30",
    "event_date": "2026-06-03",
    "embed_name": "ESPN 5 | OP2"
  },
  {
    "title": " MLB – Minnesota Twins vs Chicago White Sox - ESPN 5 | OP3",
    "url": "https://rm8zcvk3.fubohd.com:443/espn5/mono.m3u8?token=258c6400de0538926199221a178485a0b56e3f6c-86-1780502038-1780484038",
    "type": "event",
    "source": "https://tvtvhd.com/vivo/canales.php?stream=espn5",
    "country": "MLB Preseason",
    "event_description": " MLB – Minnesota Twins vs Chicago White Sox",
    "event_hour": "14:30",
    "event_date": "2026-06-03",
    "embed_name": "ESPN 5 | OP3"
  },
  {
    "title": "ESPN (LATINOAMERICA)",
    "url": "https://rm8zcvk3.fubohd.com:443/espn/mono.m3u8?token=acf8ac46b5c8a5fe23df36ca339ebe3fe2aa9bc2-db-1780502039-1780484039",
    "type": "channel",
    "source": "https://tvtvhd.com/vivo/canales.php?stream=espn",
    "country": "LATINOAMERICA",
    "status": "Activo"
  },
  {
    "title": "ESPN 2 (LATINOAMERICA)",
    "url": "https://qzv4jmsc.fubohd.com:443/espn2/mono.m3u8?token=d6d8488bb2bfadaecfd3d4f91b965fcd56f57faf-d1-1780502039-1780484039",
    "type": "channel",
    "source": "https://tvtvhd.com/vivo/canales.php?stream=espn2",
    "country": "LATINOAMERICA",
    "status": "Activo"
  },
  {
    "title": "ESPN 3 (LATINOAMERICA)",
    "url": "https://cgxheq.fubohd.com:443/espn3/mono.m3u8?token=a49f2b3d678c2bacfbfe0453407adbeed0d051cb-9a-1780502039-1780484039",
    "type": "channel",
    "source": "https://tvtvhd.com/vivo/canales.php?stream=espn3",
    "country": "LATINOAMERICA",
    "status": "Activo"
  },
  {
    "title": "ESPN 4 (LATINOAMERICA)",
    "url": "https://dw5pdgvk.fubohd.com:443/espn4/mono.m3u8?token=3588298ebab94752ca5154b574f609c13fbcae67-cc-1780502040-1780484040",
    "type": "channel",
    "source": "https://tvtvhd.com/vivo/canales.php?stream=espn4",
    "country": "LATINOAMERICA",
    "status": "Activo"
  },
  {
    "title": "ESPN 5 (LATINOAMERICA)",
    "url": "https://c2nvdxq.fubohd.com:443/espn5/mono.m3u8?token=92bc561b9154bedd13e179f48dbea072601d5d5d-72-1780502040-1780484040",
    "type": "channel",
    "source": "https://tvtvhd.com/vivo/canales.php?stream=espn5",
    "country": "LATINOAMERICA",
    "status": "Activo"
  },
  {
    "title": "ESPN 6 (LATINOAMERICA)",
    "url": "https://rm8zcvk3.fubohd.com:443/espn6/mono.m3u8?token=92f2baf6da7877cf9f40aa429f217dc90b048975-a2-1780502041-1780484041",
    "type": "channel",
    "source": "https://tvtvhd.com/vivo/canales.php?stream=espn6",
    "country": "LATINOAMERICA",
    "status": "Activo"
  },
  {
    "title": "ESPN 7 (LATINOAMERICA)",
    "url": "https://c2nvdxq.fubohd.com:443/espn7/mono.m3u8?token=45cbdcf754fc730f2af8e8b1392c83d6d38c51ad-c1-1780502041-1780484041",
    "type": "channel",
    "source": "https://tvtvhd.com/vivo/canales.php?stream=espn7",
    "country": "LATINOAMERICA",
    "status": "Activo"
  },
  {
    "title": "DSports (LATINOAMERICA)",
    "url": "https://ag9wzq.fubohd.com:443/dsports/mono.m3u8?token=dfe2a4ce54a2bd929bc89b84109c0f0a2232fa54-7d-1780502042-1780484042",
    "type": "channel",
    "source": "https://tvtvhd.com/vivo/canales.php?stream=dsports",
    "country": "LATINOAMERICA",
    "status": "Activo"
  },
  {
    "title": "DSports 2 (LATINOAMERICA)",
    "url": "https://bGFuZQ.fubohd.com:443/dsports2/mono.m3u8?token=90d8515072c510c20abb25198d4e5f4433c6f565-7b-1780502042-1780484042",
    "type": "channel",
    "source": "https://tvtvhd.com/vivo/canales.php?stream=dsports2",
    "country": "LATINOAMERICA",
    "status": "Activo"
  },
  {
    "title": "GOLTV (LATINOAMERICA)",
    "url": "https://tyg2mnl9.fubohd.com:443/goltv/mono.m3u8?token=59d7a5c7a10d575641a0cf4b03f3e432cd594b24-36-1780502042-1780484042",
    "type": "channel",
    "source": "https://tvtvhd.com/vivo/canales.php?stream=goltv",
    "country": "LATINOAMERICA",
    "status": "Activo"
  },
  {
    "title": "VTV Plus (LATINOAMERICA)",
    "url": "https://bGFuZQ.fubohd.com:443/vtvplus/mono.m3u8?token=d257fdc2ab7dc62af9bf42671069bed7caf1140d-24-1780502043-1780484043",
    "type": "channel",
    "source": "https://tvtvhd.com/vivo/canales.php?stream=vtvplus",
    "country": "LATINOAMERICA",
    "status": "Activo"
  },
  {
    "title": "Fox Sports (ARGENTINA)",
    "url": "https://anvtcax.fubohd.com:443/foxsports/mono.m3u8?token=25955152713a41ce97f7b1777aa60a14fabfe91a-d2-1780502043-1780484043",
    "type": "channel",
    "source": "https://tvtvhd.com/vivo/canales.php?stream=foxsports",
    "country": "ARGENTINA",
    "status": "Activo"
  },
  {
    "title": "Fox Sports 2 (ARGENTINA)",
    "url": "https://bGFuZQ.fubohd.com:443/foxsports2/mono.m3u8?token=76b9b3ab7523f12efb3628a3e010e9402b675116-37-1780502044-1780484044",
    "type": "channel",
    "source": "https://tvtvhd.com/vivo/canales.php?stream=foxsports2",
    "country": "ARGENTINA",
    "status": "Activo"
  },
  {
    "title": "Fox Sports 3 (ARGENTINA)",
    "url": "https://cgxheq.fubohd.com:443/foxsports3/mono.m3u8?token=b45db2f2f827d5439130bbce8f258e9838c642c5-3b-1780502044-1780484044",
    "type": "channel",
    "source": "https://tvtvhd.com/vivo/canales.php?stream=foxsports3",
    "country": "ARGENTINA",
    "status": "Activo"
  },
  {
    "title": "TNT Sports (ARGENTINA)",
    "url": "https://bGFuZQ.fubohd.com:443/tntsports/mono.m3u8?token=07fd9992de1f806845157dee9df18dadcb05cbba-91-1780502044-1780484044",
    "type": "channel",
    "source": "https://tvtvhd.com/vivo/canales.php?stream=tntsports",
    "country": "ARGENTINA",
    "status": "Activo"
  },
  {
    "title": "ESPN Premium (ARGENTINA)",
    "url": "https://bGFuZQ.fubohd.com:443/espnpremium/mono.m3u8?token=07c7ae4ecb75c3f4e46619beb77afe59425e7d6b-4e-1780502045-1780484045",
    "type": "channel",
    "source": "https://tvtvhd.com/vivo/canales.php?stream=espnpremium",
    "country": "ARGENTINA",
    "status": "Activo"
  },
  {
    "title": "TyC Sports (ARGENTINA)",
    "url": "https://x4bnd7lq.fubohd.com:443/tycsports/mono.m3u8?token=e69c40f87ba74da2b7fe1c9e448779027a567e6f-31-1780502045-1780484045",
    "type": "channel",
    "source": "https://tvtvhd.com/vivo/canales.php?stream=tycsports",
    "country": "ARGENTINA",
    "status": "Activo"
  },
  {
    "title": "TyC Sports Internacional (USA) (ARGENTINA)",
    "url": "https://anvtcax.fubohd.com:443/tycinternacional/mono.m3u8?token=a580b1927b51694c552bd8baccb5786e8a7c3a57-f4-1780502046-1780484046",
    "type": "channel",
    "source": "https://tvtvhd.com/vivo/canales.php?stream=tycinternacional",
    "country": "ARGENTINA",
    "status": "Activo"
  },
  {
    "title": "Telefe (ARGENTINA)",
    "url": "https://ag9wzq.fubohd.com:443/telefe/mono.m3u8?token=f2b2e64760cf68b98dd7c52244ad5aef1b0e227e-ad-1780502046-1780484046",
    "type": "channel",
    "source": "https://tvtvhd.com/vivo/canales.php?stream=telefe",
    "country": "ARGENTINA",
    "status": "Activo"
  },
  {
    "title": "GOLPERU (PERÚ)",
    "url": "https://aw1wcm92zq.fubohd.com:443/golperu/mono.m3u8?token=4fe6e91e721b03cfea3ef034c888b43e6cef9fd6-2-1780502047-1780484047",
    "type": "channel",
    "source": "https://tvtvhd.com/vivo/canales.php?stream=golperu",
    "country": "PERÚ",
    "status": "Activo"
  },
  {
    "title": "Liga1 MAX (PERÚ)",
    "url": "https://agvyby.fubohd.com:443/liga1max/mono.m3u8?token=21fd12f1f56aaa2fdf6b4762aa03da15a8291df4-ef-1780502047-1780484047",
    "type": "channel",
    "source": "https://tvtvhd.com/vivo/canales.php?stream=liga1max",
    "country": "PERÚ",
    "status": "Activo"
  },
  {
    "title": "Movistar Deportes (PERÚ)",
    "url": "https://c2nvdxq.fubohd.com:443/movistar/mono.m3u8?token=1c7c497bb7e1366211e8b744b6ec6919cfa3a928-1c-1780502047-1780484047",
    "type": "channel",
    "source": "https://tvtvhd.com/vivo/canales.php?stream=movistar",
    "country": "PERÚ",
    "status": "Activo"
  },
  {
    "title": "Win Sports plus (2) (COLOMBIA)",
    "url": "https://ag9wzq.fubohd.com:443/winsports2/mono.m3u8?token=d48dce5989f106751373428dae40574f00891a9a-87-1780502048-1780484048",
    "type": "channel",
    "source": "https://tvtvhd.com/vivo/canales.php?stream=winsports2",
    "country": "COLOMBIA",
    "status": "Activo"
  },
  {
    "title": "Fox Sports (MÉXICO)",
    "url": "https://wp9xqedt.fubohd.com:443/foxsportsmx/mono.m3u8?token=22887ec593070d63737c5e174da90e17d39ce15c-21-1780502048-1780484048",
    "type": "channel",
    "source": "https://tvtvhd.com/vivo/canales.php?stream=foxsportsmx",
    "country": "MÉXICO",
    "status": "Activo"
  },
  {
    "title": "Fox Sports 2 (MÉXICO)",
    "url": "https://c2nvdxq.fubohd.com:443/foxsports2mx/mono.m3u8?token=2311807375ada41126ba761cbb5769ce48b260b3-c8-1780502049-1780484049",
    "type": "channel",
    "source": "https://tvtvhd.com/vivo/canales.php?stream=foxsports2mx",
    "country": "MÉXICO",
    "status": "Activo"
  },
  {
    "title": "Fox Sports 3 (MÉXICO)",
    "url": "https://x4bnd7lq.fubohd.com:443/foxsports3mx/mono.m3u8?token=3ab333b65124472ef7f48b9fca59202064df58ac-65-1780502049-1780484049",
    "type": "channel",
    "source": "https://tvtvhd.com/vivo/canales.php?stream=foxsports3mx",
    "country": "MÉXICO",
    "status": "Activo"
  },
  {
    "title": "Fox Sports Premium (MÉXICO)",
    "url": "https://bGFuZQ.fubohd.com:443/foxsportspremium/mono.m3u8?token=196c97077aa0526a2c37e5de15f777eea733d78f-28-1780502050-1780484050",
    "type": "channel",
    "source": "https://tvtvhd.com/vivo/canales.php?stream=foxsportspremium",
    "country": "MÉXICO",
    "status": "Activo"
  },
  {
    "title": "ESPN (MÉXICO)",
    "url": "https://rm8zcvk3.fubohd.com:443/espnmx/mono.m3u8?token=6e4b1f05c76f10a9a8aee73af47e6b3f4fc163f5-6a-1780502050-1780484050",
    "type": "channel",
    "source": "https://tvtvhd.com/vivo/canales.php?stream=espnmx",
    "country": "MÉXICO",
    "status": "Activo"
  },
  {
    "title": "ESPN 2 (MÉXICO)",
    "url": "https://qzv4jmsc.fubohd.com:443/espn2mx/mono.m3u8?token=e82357b8f8d689d09a6affd64be511551cc3c58a-63-1780502050-1780484050",
    "type": "channel",
    "source": "https://tvtvhd.com/vivo/canales.php?stream=espn2mx",
    "country": "MÉXICO",
    "status": "Activo"
  },
  {
    "title": "ESPN 3 (MÉXICO)",
    "url": "https://agvyby.fubohd.com:443/espn3mx/mono.m3u8?token=adc63528fb0b13e4be652724eda34cdc5531d25f-82-1780502051-1780484051",
    "type": "channel",
    "source": "https://tvtvhd.com/vivo/canales.php?stream=espn3mx",
    "country": "MÉXICO",
    "status": "Activo"
  },
  {
    "title": "ESPN 4 (MÉXICO)",
    "url": "https://x4bnd7lq.fubohd.com:443/espn4mx/mono.m3u8?token=69d0674d533f006b7397c6da0c73047b71b71227-a6-1780502051-1780484051",
    "type": "channel",
    "source": "https://tvtvhd.com/vivo/canales.php?stream=espn4mx",
    "country": "MÉXICO",
    "status": "Activo"
  },
  {
    "title": "Azteca 7 (MÉXICO)",
    "url": "https://c2nvdxq.fubohd.com:443/azteca7/mono.m3u8?token=fb664da5c476ff6e14ccaae964458f6712e12982-f0-1780502052-1780484052",
    "type": "channel",
    "source": "https://tvtvhd.com/vivo/canales.php?stream=azteca7",
    "country": "MÉXICO",
    "status": "Activo"
  },
  {
    "title": "Canal 5 (MÉXICO)",
    "url": "https://agvyby.fubohd.com:443/canal5/mono.m3u8?token=240a9e5ed5823bd9b1bdd1c734927c4614af244d-29-1780502052-1780484052",
    "type": "channel",
    "source": "https://tvtvhd.com/vivo/canales.php?stream=canal5",
    "country": "MÉXICO",
    "status": "Activo"
  },
  {
    "title": "Azteca Deportes (MÉXICO)",
    "url": "https://ym9yzq.fubohd.com:443/azteca_deportes/mono.m3u8?token=83c401791d16c9e3f922654325622a8e3c2fe291-2-1780502053-1780484053",
    "type": "channel",
    "source": "https://tvtvhd.com/vivo/canales.php?stream=azteca_deportes",
    "country": "MÉXICO",
    "status": "Activo"
  },
  {
    "title": "Fox Deportes (USA)",
    "url": "https://c2nvdxq.fubohd.com:443/foxdeportes/mono.m3u8?token=89e6ea5eccec36228dfc851a88db0ab529a60eea-c0-1780502053-1780484053",
    "type": "channel",
    "source": "https://tvtvhd.com/vivo/canales.php?stream=foxdeportes",
    "country": "USA",
    "status": "Activo"
  },
  {
    "title": "ESPN Deportes (USA)",
    "url": "https://a2vlca.fubohd.com:443/espndeportes/mono.m3u8?token=d993ce7cb8f63a7309ada444b36c8053e6022ed9-68-1780502053-1780484053",
    "type": "channel",
    "source": "https://tvtvhd.com/vivo/canales.php?stream=espndeportes",
    "country": "USA",
    "status": "Activo"
  },
  {
    "title": "TUDN (USA)",
    "url": "https://rm8zcvk3.fubohd.com:443/tudn/mono.m3u8?token=dcb7631d24b483eed4adaceb9416dd40c5907107-af-1780502054-1780484054",
    "type": "channel",
    "source": "https://tvtvhd.com/vivo/canales.php?stream=tudn",
    "country": "USA",
    "status": "Activo"
  },
  {
    "title": "BeIN Sports Español (USA)",
    "url": "https://x4bnd7lq.fubohd.com:443/beinsportes/mono.m3u8?token=a8d456c2bacfeadd9b754d8539f2c9fb77b40572-3f-1780502054-1780484054",
    "type": "channel",
    "source": "https://tvtvhd.com/vivo/canales.php?stream=beinsportes",
    "country": "USA",
    "status": "Activo"
  },
  {
    "title": "Unimás (USA)",
    "url": "https://anvtcax.fubohd.com:443/unimas/mono.m3u8?token=1cbda34c315a7ccb92dc342e8d46d047b5792a03-71-1780502055-1780484055",
    "type": "channel",
    "source": "https://tvtvhd.com/vivo/canales.php?stream=unimas",
    "country": "USA",
    "status": "Activo"
  },
  {
    "title": "BeIN Sports Xtra Español (USA)",
    "url": "https://anvtcax.fubohd.com:443/beinsport_xtra_espanol/mono.m3u8?token=285be5f7cda6c6bcf7e920bed96e484fada55ee5-36-1780502055-1780484055",
    "type": "channel",
    "source": "https://tvtvhd.com/vivo/canales.php?stream=beinsport_xtra_espanol",
    "country": "USA",
    "status": "Activo"
  },
  {
    "title": "USAnetwork (USA)",
    "url": "https://dw5pdgvk.fubohd.com:443/usanetwork/mono.m3u8?token=a9b4c876164ce56da826a67db04e692ff8a3841a-ed-1780502056-1780484056",
    "type": "channel",
    "source": "https://tvtvhd.com/vivo/canales.php?stream=usanetwork",
    "country": "USA",
    "status": "Activo"
  },
  {
    "title": "Telemundo (USA)",
    "url": "https://qzv4jmsc.fubohd.com:443/telemundo/mono.m3u8?token=4574e5899649a86e06a5252447d619979402e91c-9f-1780502056-1780484056",
    "type": "channel",
    "source": "https://tvtvhd.com/vivo/canales.php?stream=telemundo",
    "country": "USA",
    "status": "Activo"
  },
  {
    "title": "Premiere 1 (BRASIL)",
    "url": "https://wp9xqedt.fubohd.com:443/premiere1/mono.m3u8?token=25baa1b19e604aa1090f7dd90a50f63ede728ed2-d7-1780502056-1780484056",
    "type": "channel",
    "source": "https://tvtvhd.com/vivo/canales.php?stream=premiere1",
    "country": "BRASIL",
    "status": "Activo"
  },
  {
    "title": "Premiere 2 (BRASIL)",
    "url": "https://c2nvdxq.fubohd.com:443/premiere2/mono.m3u8?token=9da2ca292e4d9ed57fef99aa7c4592a69c8a6446-71-1780502057-1780484057",
    "type": "channel",
    "source": "https://tvtvhd.com/vivo/canales.php?stream=premiere2",
    "country": "BRASIL",
    "status": "Activo"
  },
  {
    "title": "Premiere 3 (BRASIL)",
    "url": "https://tyg2mnl9.fubohd.com:443/premiere3/mono.m3u8?token=c42694cdbb62d0237f6313d66b430434fb079949-a4-1780502057-1780484057",
    "type": "channel",
    "source": "https://tvtvhd.com/vivo/canales.php?stream=premiere3",
    "country": "BRASIL",
    "status": "Activo"
  },
  {
    "title": "Premiere 5 (BRASIL)",
    "url": "https://qzv4jmsc.fubohd.com:443/premiere5/mono.m3u8?token=5033c90d3642d9b756fbe5678c44a18fd3e0fa9f-1f-1780502058-1780484058",
    "type": "channel",
    "source": "https://tvtvhd.com/vivo/canales.php?stream=premiere5",
    "country": "BRASIL",
    "status": "Activo"
  },
  {
    "title": "Sportv (BRASIL)",
    "url": "https://anvtcax.fubohd.com:443/sportv/mono.m3u8?token=7d0db9b07aa13ccad551f6f2eacd1ec66f6dc055-ef-1780502058-1780484058",
    "type": "channel",
    "source": "https://tvtvhd.com/vivo/canales.php?stream=sportv",
    "country": "BRASIL",
    "status": "Activo"
  },
  {
    "title": "Sportv 2 (BRASIL)",
    "url": "https://cgxheq.fubohd.com:443/sportv2/mono.m3u8?token=9059db7e952e716b6a78c3776f932ec76719e8a4-fb-1780502058-1780484058",
    "type": "channel",
    "source": "https://tvtvhd.com/vivo/canales.php?stream=sportv2",
    "country": "BRASIL",
    "status": "Activo"
  },
  {
    "title": "Sportv 3 (BRASIL)",
    "url": "https://x4bnd7lq.fubohd.com:443/sportv3/mono.m3u8?token=202c00d4e298a70a942b61e5172a5d066e9319ad-ca-1780502059-1780484059",
    "type": "channel",
    "source": "https://tvtvhd.com/vivo/canales.php?stream=sportv3",
    "country": "BRASIL",
    "status": "Activo"
  },
  {
    "title": "ESPN 1 NL (MUNDO)",
    "url": "https://qzv4jmsc.fubohd.com:443/espn1_nl/mono.m3u8?token=8c16ffdea2ce84c243b134dfdf2c8b9a256f50d5-c1-1780502059-1780484059",
    "type": "channel",
    "source": "https://tvtvhd.com/vivo/canales.php?stream=espn1_nl",
    "country": "MUNDO",
    "status": "Activo"
  },
  {
    "title": "ESPN 2 NL (MUNDO)",
    "url": "https://cgxheq.fubohd.com:443/espn2_nl/mono.m3u8?token=36a158dea23e2a564c3e70334b9da1657e8adcf2-e1-1780502060-1780484060",
    "type": "channel",
    "source": "https://tvtvhd.com/vivo/canales.php?stream=espn2_nl",
    "country": "MUNDO",
    "status": "Activo"
  },
  {
    "title": "ESPN 3 NL (MUNDO)",
    "url": "https://dw5pdgvk.fubohd.com:443/espn3_nl/mono.m3u8?token=755fc791665985186af664640d3f6dbd854b3ef7-79-1780502060-1780484060",
    "type": "channel",
    "source": "https://tvtvhd.com/vivo/canales.php?stream=espn3_nl",
    "country": "MUNDO",
    "status": "Activo"
  }
]