[
  {
    "title": "F2 Spa-Francorchamps – Práctica - ESPN 2",
    "url": "https://cxm8.futbolonlinehd.com:443/even6/mono.m3u8?token=a27355d392f5549ec14d747828e1742934172a90-6e-1784293329-1784275329",
    "type": "event",
    "source": "https://fltvhd.com/online/canal.php?stream=even6",
    "country": "Formula 2",
    "event_description": "F2 Spa-Francorchamps – Práctica",
    "event_hour": "05:50",
    "event_date": "2026-07-17",
    "embed_name": "ESPN 2"
  },
  {
    "title": "F2 Spa-Francorchamps – Práctica - ESPN 2 | OP2",
    "url": "https://cxm6.futbolonlinehd.com:443/even6/mono.m3u8?token=e110a78d5e928bc84150cbea468537c2b1d60001-5-1784293329-1784275329",
    "type": "event",
    "source": "https://fltvhd.com/online/canal.php?stream=even6",
    "country": "Formula 2",
    "event_description": "F2 Spa-Francorchamps – Práctica",
    "event_hour": "05:50",
    "event_date": "2026-07-17",
    "embed_name": "ESPN 2 | OP2"
  },
  {
    "title": "F2 Spa-Francorchamps – Práctica - ESPN 2 | OP3",
    "url": "https://cxm1.futbolonlinehd.com:443/even6/mono.m3u8?token=386d995c783286c5f46b2d3731b26f485af9ea2a-ec-1784293330-1784275330",
    "type": "event",
    "source": "https://fltvhd.com/online/canal.php?stream=even6",
    "country": "Formula 2",
    "event_description": "F2 Spa-Francorchamps – Práctica",
    "event_hour": "05:50",
    "event_date": "2026-07-17",
    "embed_name": "ESPN 2 | OP3"
  },
  {
    "title": "F3 Spa-Francorchamps – Clasificación - ESPN 3",
    "url": "https://cxm8.futbolonlinehd.com:443/even7/mono.m3u8?token=5ee352b415b6611844369951e65a03768465d5f9-31-1784293330-1784275330",
    "type": "event",
    "source": "https://fltvhd.com/online/canal.php?stream=even7",
    "country": "Formula 2",
    "event_description": "F3 Spa-Francorchamps – Clasificación",
    "event_hour": "09:55",
    "event_date": "2026-07-17",
    "embed_name": "ESPN 3"
  },
  {
    "title": "F3 Spa-Francorchamps – Clasificación - ESPN 3 | OP2",
    "url": "https://cxm8.futbolonlinehd.com:443/even7/mono.m3u8?token=4325511a728866362942169223a687a2b90c9e07-bd-1784293330-1784275330",
    "type": "event",
    "source": "https://fltvhd.com/online/canal.php?stream=even7",
    "country": "Formula 2",
    "event_description": "F3 Spa-Francorchamps – Clasificación",
    "event_hour": "09:55",
    "event_date": "2026-07-17",
    "embed_name": "ESPN 3 | OP2"
  },
  {
    "title": "F3 Spa-Francorchamps – Clasificación - ESPN 3 | OP3",
    "url": "https://cxm4.futbolonlinehd.com:443/even7/mono.m3u8?token=7f0435f832654f6539112a68a067ac9d348b53b4-39-1784293331-1784275331",
    "type": "event",
    "source": "https://fltvhd.com/online/canal.php?stream=even7",
    "country": "Formula 2",
    "event_description": "F3 Spa-Francorchamps – Clasificación",
    "event_hour": "09:55",
    "event_date": "2026-07-17",
    "embed_name": "ESPN 3 | OP3"
  },
  {
    "title": "F2 Spa-Francorchamps – Clasificación - ESPN 3",
    "url": "https://cxm7.futbolonlinehd.com:443/even7/mono.m3u8?token=5249e44ab9bedb1f2f0a0c4dc010881120df1ff5-e8-1784293331-1784275331",
    "type": "event",
    "source": "https://fltvhd.com/online/canal.php?stream=even7",
    "country": "Formula 2",
    "event_description": "F2 Spa-Francorchamps – Clasificación",
    "event_hour": "10:40",
    "event_date": "2026-07-17",
    "embed_name": "ESPN 3"
  },
  {
    "title": "F2 Spa-Francorchamps – Clasificación - ESPN 3 | OP2",
    "url": "https://cxm2.futbolonlinehd.com:443/even7/mono.m3u8?token=dc2951138954a3bf5f814fe4d6b219c01c74f9de-4-1784293332-1784275332",
    "type": "event",
    "source": "https://fltvhd.com/online/canal.php?stream=even7",
    "country": "Formula 2",
    "event_description": "F2 Spa-Francorchamps – Clasificación",
    "event_hour": "10:40",
    "event_date": "2026-07-17",
    "embed_name": "ESPN 3 | OP2"
  },
  {
    "title": "F2 Spa-Francorchamps – Clasificación - ESPN 3 | OP3",
    "url": "https://cxm7.futbolonlinehd.com:443/even7/mono.m3u8?token=fbf3cb440d61470c4aee0bea2c612b70e7aa54a5-71-1784293332-1784275332",
    "type": "event",
    "source": "https://fltvhd.com/online/canal.php?stream=even7",
    "country": "Formula 2",
    "event_description": "F2 Spa-Francorchamps – Clasificación",
    "event_hour": "10:40",
    "event_date": "2026-07-17",
    "embed_name": "ESPN 3 | OP3"
  },
  {
    "title": " F3 Spa-Francorchamps – Práctica - ESPN 2",
    "url": "https://cxm1.futbolonlinehd.com:443/even6/mono.m3u8?token=41d8b067a0680088b793af837e43b6219d931b0b-8f-1784293341-1784275341",
    "type": "event",
    "source": "https://fltvhd.com/online/canal.php?stream=even6",
    "country": "Formula 2",
    "event_description": " F3 Spa-Francorchamps – Práctica",
    "event_hour": "04:50",
    "event_date": "2026-07-17",
    "embed_name": "ESPN 2"
  },
  {
    "title": " F3 Spa-Francorchamps – Práctica - ESPN 2 | OP2",
    "url": "https://cxm5.futbolonlinehd.com:443/even6/mono.m3u8?token=4a089b4c86dd4619c8435d381e3568d9fbc25d93-3-1784293341-1784275341",
    "type": "event",
    "source": "https://fltvhd.com/online/canal.php?stream=even6",
    "country": "Formula 2",
    "event_description": " F3 Spa-Francorchamps – Práctica",
    "event_hour": "04:50",
    "event_date": "2026-07-17",
    "embed_name": "ESPN 2 | OP2"
  },
  {
    "title": " F3 Spa-Francorchamps – Práctica - ESPN 2 | OP3",
    "url": "https://cxm3.futbolonlinehd.com:443/even6/mono.m3u8?token=8c814db0a855a8cb313af44159d7b2c0755b8d2c-b8-1784293342-1784275342",
    "type": "event",
    "source": "https://fltvhd.com/online/canal.php?stream=even6",
    "country": "Formula 2",
    "event_description": " F3 Spa-Francorchamps – Práctica",
    "event_hour": "04:50",
    "event_date": "2026-07-17",
    "embed_name": "ESPN 2 | OP3"
  },
  {
    "title": "Ciclismo – Tour de France – Etapa #13 - ESPN 2",
    "url": "https://cxm8.futbolonlinehd.com:443/even6/mono.m3u8?token=28cf9f607a271cfe3f53217093167750c32865f4-1a-1784293342-1784275342",
    "type": "event",
    "source": "https://fltvhd.com/online/canal.php?stream=even6",
    "country": "Ciclismo",
    "event_description": "Ciclismo – Tour de France – Etapa #13",
    "event_hour": "07:30",
    "event_date": "2026-07-17",
    "embed_name": "ESPN 2"
  },
  {
    "title": "Ciclismo – Tour de France – Etapa #13 - ESPN 2 | OP2",
    "url": "https://cxm1.futbolonlinehd.com:443/even6/mono.m3u8?token=4d2dee18a6016d78452913d8090e08e3d4f6b306-9b-1784293343-1784275343",
    "type": "event",
    "source": "https://fltvhd.com/online/canal.php?stream=even6",
    "country": "Ciclismo",
    "event_description": "Ciclismo – Tour de France – Etapa #13",
    "event_hour": "07:30",
    "event_date": "2026-07-17",
    "embed_name": "ESPN 2 | OP2"
  },
  {
    "title": "Ciclismo – Tour de France – Etapa #13 - ESPN 2 | OP3",
    "url": "https://cxm8.futbolonlinehd.com:443/even6/mono.m3u8?token=8a05b8df481636fd71a10c1b38ff995d5f880bd0-f5-1784293343-1784275343",
    "type": "event",
    "source": "https://fltvhd.com/online/canal.php?stream=even6",
    "country": "Ciclismo",
    "event_description": "Ciclismo – Tour de France – Etapa #13",
    "event_hour": "07:30",
    "event_date": "2026-07-17",
    "embed_name": "ESPN 2 | OP3"
  },
  {
    "title": "Golf – The Open Championship – Segunda Vuelta - ESPN 2",
    "url": "https://cxm3.futbolonlinehd.com:443/even6/mono.m3u8?token=c8eda1bb4b2deb2027d88e3add797f7ada8cc4b0-50-1784293343-1784275343",
    "type": "event",
    "source": "https://fltvhd.com/online/canal.php?stream=even6",
    "country": "Golf",
    "event_description": "Golf – The Open Championship – Segunda Vuelta",
    "event_hour": "13:30",
    "event_date": "2026-07-17",
    "embed_name": "ESPN 2"
  },
  {
    "title": "Golf – The Open Championship – Segunda Vuelta - ESPN 2 | OP2",
    "url": "https://cxm1.futbolonlinehd.com:443/even6/mono.m3u8?token=92690dd7aa195e6cd305d0065da4dffcb215a9b7-0-1784293344-1784275344",
    "type": "event",
    "source": "https://fltvhd.com/online/canal.php?stream=even6",
    "country": "Golf",
    "event_description": "Golf – The Open Championship – Segunda Vuelta",
    "event_hour": "13:30",
    "event_date": "2026-07-17",
    "embed_name": "ESPN 2 | OP2"
  },
  {
    "title": "Golf – The Open Championship – Segunda Vuelta - ESPN 2 | OP3",
    "url": "https://cxm1.futbolonlinehd.com:443/even6/mono.m3u8?token=edecf6a329c054e4817629a00d4f094f01a59c47-1d-1784293344-1784275344",
    "type": "event",
    "source": "https://fltvhd.com/online/canal.php?stream=even6",
    "country": "Golf",
    "event_description": "Golf – The Open Championship – Segunda Vuelta",
    "event_hour": "13:30",
    "event_date": "2026-07-17",
    "embed_name": "ESPN 2 | OP3"
  },
  {
    "title": "ESPN Knockout – A Confirmar - ESPN 2",
    "url": "https://cxm2.futbolonlinehd.com:443/even6/mono.m3u8?token=b4f7fca440e1fcefcf6f4b82894cdc1cf2df1c12-92-1784293345-1784275345",
    "type": "event",
    "source": "https://fltvhd.com/online/canal.php?stream=even6",
    "country": "Boxeo",
    "event_description": "ESPN Knockout – A Confirmar",
    "event_hour": "21:00",
    "event_date": "2026-07-17",
    "embed_name": "ESPN 2"
  },
  {
    "title": "ESPN Knockout – A Confirmar - ESPN 2 | OP2",
    "url": "https://cxm9.futbolonlinehd.com:443/even6/mono.m3u8?token=3c93b061a90454fd9dc674892084eaf83ba3479b-79-1784293345-1784275345",
    "type": "event",
    "source": "https://fltvhd.com/online/canal.php?stream=even6",
    "country": "Boxeo",
    "event_description": "ESPN Knockout – A Confirmar",
    "event_hour": "21:00",
    "event_date": "2026-07-17",
    "embed_name": "ESPN 2 | OP2"
  },
  {
    "title": "ESPN Knockout – A Confirmar - ESPN 2 | OP3",
    "url": "https://cxm1.futbolonlinehd.com:443/even6/mono.m3u8?token=ee11894a76b420974155d0ad183970f052ed7ce2-fe-1784293345-1784275345",
    "type": "event",
    "source": "https://fltvhd.com/online/canal.php?stream=even6",
    "country": "Boxeo",
    "event_description": "ESPN Knockout – A Confirmar",
    "event_hour": "21:00",
    "event_date": "2026-07-17",
    "embed_name": "ESPN 2 | OP3"
  }
]